greeks_package/__init__.py
greeks_package/core.py
greeks_package/plotting.py
greeks_package/pricing.py
greeks_package/setup.py
greeks_package-1.1.0.dist-info/licenses/LICENSE
greeks_package-1.1.0.dist-info/METADATA
greeks_package-1.1.0.dist-info/WHEEL
greeks_package-1.1.0.dist-info/top_level.txt
greeks_package-1.1.0.dist-info/RECORD
