Metadata-Version: 2.4
Name: greeks-package
Version: 1.1.0
Summary: Black-Scholes option Greeks made easy - comprehensive Greek calculations for European options
Home-page: https://github.com/JRCon1/greeks-package
Author: JR Concepcion
Author-email: JR Concepcion <jr1concepcion@gmail.com>
Maintainer-email: JR Concepcion <jr1concepcion@gmail.com>
License: MIT License
Project-URL: Homepage, https://github.com/JRCon1/greeks-package
Project-URL: Documentation, https://github.com/JRCon1/greeks-package/blob/main/greeks_package%201.0.1/README.md
Project-URL: Repository, https://github.com/JRCon1/greeks-package
Project-URL: Tutorial (v0.1.0), https://youtu.be/geyCTGodXQk?si=zT3s4Gf2bMmGQk4I
Keywords: options,greeks,black-scholes,finance,derivatives,quantitative,trading,risk-management,delta,gamma,vega,theta,volatility,options-pricing
Classifier: Development Status :: 5 - Production/Stable
Classifier: Intended Audience :: Financial and Insurance Industry
Classifier: Intended Audience :: Developers
Classifier: Intended Audience :: Science/Research
Classifier: License :: OSI Approved :: MIT License
Classifier: Operating System :: OS Independent
Classifier: Programming Language :: Python :: 3
Classifier: Programming Language :: Python :: 3.9
Classifier: Programming Language :: Python :: 3.10
Classifier: Programming Language :: Python :: 3.11
Classifier: Programming Language :: Python :: 3.12
Classifier: Topic :: Office/Business :: Financial
Classifier: Topic :: Scientific/Engineering :: Mathematics
Classifier: Topic :: Software Development :: Libraries :: Python Modules
Requires-Python: >=3.9
License-File: LICENSE
Requires-Dist: numpy>=1.23
Requires-Dist: pandas>=1.5
Requires-Dist: scipy>=1.10
Requires-Dist: yfinance>=0.2
Requires-Dist: plotly>=5.19
Provides-Extra: dev
Requires-Dist: pytest>=7.0; extra == "dev"
Requires-Dist: pytest-cov>=4.0; extra == "dev"
Requires-Dist: black>=22.0; extra == "dev"
Requires-Dist: flake8>=5.0; extra == "dev"
Requires-Dist: mypy>=1.0; extra == "dev"
Requires-Dist: jupyter>=1.0; extra == "dev"
Provides-Extra: docs
Requires-Dist: sphinx>=5.0; extra == "docs"
Requires-Dist: sphinx-rtd-theme>=1.0; extra == "docs"
Requires-Dist: sphinx-autoapi>=2.0; extra == "docs"
Dynamic: author
Dynamic: home-page
Dynamic: license-file
Dynamic: requires-python
